airflow_provider_kafka/__init__.py
airflow_provider_kafka/shared_utils.py
airflow_provider_kafka/hooks/__init__.py
airflow_provider_kafka/hooks/admin_client.py
airflow_provider_kafka/hooks/consumer.py
airflow_provider_kafka/hooks/producer.py
airflow_provider_kafka/operators/__init__.py
airflow_provider_kafka/operators/await_message.py
airflow_provider_kafka/operators/consume_from_topic.py
airflow_provider_kafka/operators/event_triggers_function.py
airflow_provider_kafka/operators/produce_to_topic.py
airflow_provider_kafka/triggers/__init__.py
airflow_provider_kafka/triggers/await_message.py
airflow_provider_kafka-0.2.5.dist-info/licenses/LICENSE.txt
airflow_provider_kafka-0.2.5.dist-info/METADATA
airflow_provider_kafka-0.2.5.dist-info/WHEEL
airflow_provider_kafka-0.2.5.dist-info/top_level.txt
airflow_provider_kafka-0.2.5.dist-info/RECORD
