Metadata-Version: 2.4
Name: airflow-provider-kafka
Version: 0.2.5
Summary: Apache Airflow Kafka provider containing Deferrable Operators & Sensors.
Home-page: https://github.com/astronomer/airflow-provider-kafka
Author: Dylan Storey
Author-email: dylan.storey@astronomer.io
License: Apache License 2.0
Project-URL: Source Code, https://github.com/astronomer/airflow-provider-kafka
Project-URL: Homepage, https://github.com/astronomer/airflow-provider-kafka
Project-URL: Changelog, https://github.com/astronomer/airflow-provider-kafka/blob/main/CHANGELOG.md
Classifier: Development Status :: 7 - Inactive
Classifier: Environment :: Web Environment
Classifier: Intended Audience :: Developers
Classifier: License :: OSI Approved :: Apache Software License
Classifier: Operating System :: OS Independent
Classifier: Programming Language :: Python
Classifier: Programming Language :: Python :: 3
Classifier: Programming Language :: Python :: 3.7
Classifier: Programming Language :: Python :: 3.8
Classifier: Programming Language :: Python :: 3.9
Requires-Python: >=3.7
License-File: LICENSE.txt
Requires-Dist: apache-airflow>=2.2.0
Requires-Dist: asgiref
Requires-Dist: confluent-kafka>=1.8.2
Provides-Extra: dev
Requires-Dist: mypy>=0.800; extra == "dev"
Requires-Dist: pytest; extra == "dev"
Requires-Dist: pytest-cov; extra == "dev"
Requires-Dist: pre-commit; extra == "dev"
Requires-Dist: angreal; extra == "dev"
Dynamic: license-file
